remote_pb2/__init__.py
remote_pb2/remote_pb2.py
remote_pb2/types_pb2.py
remote_pb2/gogoproto/__init__.py
remote_pb2/gogoproto/gogo_pb2.py
remote_pb2-0.4.0.dist-info/licenses/LICENSE
remote_pb2-0.4.0.dist-info/METADATA
remote_pb2-0.4.0.dist-info/WHEEL
remote_pb2-0.4.0.dist-info/top_level.txt
remote_pb2-0.4.0.dist-info/RECORD
