Metadata-Version: 2.4
Name: remote-pb2
Version: 0.4.0
Summary: Generated protobuf bindings for Remote write service
Home-page: https://github.com/leegin/remote_pb2
Author: Leegin Bernads
Author-email: leegin.t@gmail.com
License: MIT
Classifier: Programming Language :: Python :: 3
Classifier: License :: OSI Approved :: MIT License
Classifier: Operating System :: OS Independent
Requires-Python: >=3.7
License-File: LICENSE
Dynamic: license-file
